ServletRumenjiaochengCYuyanBianchengWangFix1/README.md
ServletRumenjiaochengCYuyanBianchengWangFix1/__init__.py
ServletRumenjiaochengCYuyanBianchengWangFix1/__main__.py
ServletRumenjiaochengCYuyanBianchengWangFix1/file.epub
ServletRumenjiaochengCYuyanBianchengWangFix1/index.html
ServletRumenjiaochengCYuyanBianchengWangFix1/css/__init__.py
ServletRumenjiaochengCYuyanBianchengWangFix1/css/annotations.css
ServletRumenjiaochengCYuyanBianchengWangFix1/css/main.css
ServletRumenjiaochengCYuyanBianchengWangFix1/css/normalize.css
ServletRumenjiaochengCYuyanBianchengWangFix1/css/popup.css
ServletRumenjiaochengCYuyanBianchengWangFix1/font/__init__.py
ServletRumenjiaochengCYuyanBianchengWangFix1/font/fontello.eot
ServletRumenjiaochengCYuyanBianchengWangFix1/font/fontello.svg
ServletRumenjiaochengCYuyanBianchengWangFix1/font/fontello.ttf
ServletRumenjiaochengCYuyanBianchengWangFix1/font/fontello.woff
ServletRumenjiaochengCYuyanBianchengWangFix1/img/__init__.py
ServletRumenjiaochengCYuyanBianchengWangFix1/img/annotator-glyph-sprite.png
ServletRumenjiaochengCYuyanBianchengWangFix1/img/annotator-icon-sprite.png
ServletRumenjiaochengCYuyanBianchengWangFix1/img/apple-touch-icon.png
ServletRumenjiaochengCYuyanBianchengWangFix1/img/cancelfullscreen.png
ServletRumenjiaochengCYuyanBianchengWangFix1/img/close.png
ServletRumenjiaochengCYuyanBianchengWangFix1/img/fullscreen.png
ServletRumenjiaochengCYuyanBianchengWangFix1/img/loader.gif
ServletRumenjiaochengCYuyanBianchengWangFix1/img/menu-icon.png
ServletRumenjiaochengCYuyanBianchengWangFix1/img/save.png
ServletRumenjiaochengCYuyanBianchengWangFix1/img/saved.png
ServletRumenjiaochengCYuyanBianchengWangFix1/img/settings-s.png
ServletRumenjiaochengCYuyanBianchengWangFix1/img/settings.png
ServletRumenjiaochengCYuyanBianchengWangFix1/img/star.png
ServletRumenjiaochengCYuyanBianchengWangFix1/js/__init__.py
ServletRumenjiaochengCYuyanBianchengWangFix1/js/epub.js
ServletRumenjiaochengCYuyanBianchengWangFix1/js/epub.min.js
servlet_rumenjiaocheng_c_yuyan_biancheng_wang_fix1-2025.3.24.1.dist-info/METADATA
servlet_rumenjiaocheng_c_yuyan_biancheng_wang_fix1-2025.3.24.1.dist-info/WHEEL
servlet_rumenjiaocheng_c_yuyan_biancheng_wang_fix1-2025.3.24.1.dist-info/entry_points.txt
servlet_rumenjiaocheng_c_yuyan_biancheng_wang_fix1-2025.3.24.1.dist-info/top_level.txt
servlet_rumenjiaocheng_c_yuyan_biancheng_wang_fix1-2025.3.24.1.dist-info/RECORD
